{"_id":"55ee5e986efd1aa2ee974212","index":2188,"guid":"ee796168-8dae-473d-bd10-72b35d3f7772","isActive":true,"balance":"$81,111.57","picture":"http://placehold.it/32x32","age":26,"eyeColor":"brown","name":"Cox Macdonald","gender":"male","company":"DIGIGENE","email":"coxmacdonald@digigene.com","phone":"+1 (875) 479-3436","address":"269 Portal Street, Hemlock, Mississippi, 897","about":"Ipsum exercitation quis exercitation qui fugiat sint. Do Lorem esse veniam incididunt dolore nostrud cupidatat. Esse sit velit deserunt nulla do consequat. Dolor et eiusmod duis sunt elit ad laborum. Elit ipsum commodo minim dolore do est culpa laboris. Anim excepteur veniam sit minim amet reprehenderit consectetur laboris.\r\n","registered":"2015-03-06T02:31:20 -07:00","tags":["reprehenderit","eu","veniam","consectetur","magna","proident","sit"],"friends":[{"id":0,"name":"Elsa Gallagher"},{"id":1,"name":"Graves Deleon"},{"id":2,"name":"Winifred Owen"}],"greeting":"Hello, Cox Macdonald! You have 4 unread messages.","favoriteFruit":"orange","location":{"latitude":-28.108367,"longitude":55.884465},"docFormat":"json"}