{"_id":"55ee5e98e322a43247f3671f","index":2100,"guid":"3e399122-66cf-4010-babd-116329836347","isActive":false,"balance":"$41,888.07","picture":"http://placehold.it/32x32","age":51,"eyeColor":"amethyst","name":"Rosario Clarke","gender":"female","company":"ZEPITOPE","email":"rosarioclarke@zepitope.com","phone":"+1 (940) 413-3483","address":"598 Dobbin Street, Epworth, North Carolina, 1448","about":"Aliquip id fugiat minim eu elit dolore laborum veniam ipsum ex ad. Mollit aute ipsum duis tempor voluptate nostrud velit aliquip aliquip consequat mollit velit. Laboris sunt pariatur aliqua proident eu officia mollit et veniam anim veniam magna magna officia.\r\n","registered":"2014-09-24T10:45:39 -07:00","tags":["proident","et","veniam","veniam","veniam","sunt","labore"],"friends":[{"id":0,"name":"Marks Lloyd"},{"id":1,"name":"Roseann Marquez"},{"id":2,"name":"Mueller West"}],"greeting":"Hello, Rosario Clarke! You have 1 unread messages.","favoriteFruit":"orange","location":{"latitude":54.567889,"longitude":125.287481},"docFormat":"json"}