{"_id":"55ee5e98a876eff0d63fac68","index":2171,"guid":"1c9ee538-0fff-4b1a-874d-c453cf5da69d","isActive":false,"balance":"$49,493.85","picture":"http://placehold.it/32x32","age":51,"eyeColor":"green","name":"Nora Langley","gender":"female","company":"TERRAGO","email":"noralangley@terrago.com","phone":"+1 (988) 593-2030","address":"980 Columbia Street, Glendale, New Mexico, 7439","about":"Minim veniam cillum cillum officia et eiusmod consequat eiusmod aute consequat consectetur qui. Consectetur ullamco sint qui tempor cillum elit aliqua amet aliqua quis irure sit. Mollit velit laboris officia reprehenderit voluptate esse labore excepteur ut labore. Cillum velit commodo ex et in cupidatat ullamco. Laborum officia ex voluptate qui nostrud adipisicing enim reprehenderit dolore. Veniam culpa proident velit incididunt ex cupidatat reprehenderit ullamco veniam exercitation voluptate. Qui magna enim exercitation proident ut magna amet dolore minim deserunt id.\r\n","registered":"2014-03-20T08:31:34 -07:00","tags":["qui","pariatur","mollit","magna","non","velit","nostrud"],"friends":[{"id":0,"name":"Andrews Boyd"},{"id":1,"name":"Tameka Bowman"},{"id":2,"name":"Leta Carson"}],"greeting":"Hello, Nora Langley! You have 5 unread messages.","favoriteFruit":"pear","location":{"latitude":-12.623127,"longitude":36.734231},"docFormat":"json"}