{"_id":"55ee5e44357f7167e932ddac","index":855,"guid":"5ee1b83f-74ef-405c-bdad-2022952d777c","isActive":false,"balance":"$72,883.83","picture":"http://placehold.it/32x32","age":41,"eyeColor":"brown","name":"Peck Bradley","gender":"male","company":"LOCAZONE","email":"peckbradley@locazone.com","phone":"+1 (823) 564-3485","address":"879 Alton Place, Chilton, New Jersey, 1964","about":"Ad consectetur nulla irure nostrud dolor. Dolore adipisicing id duis Lorem cupidatat ea reprehenderit veniam sint cillum veniam. Tempor commodo in adipisicing aliquip laboris et quis magna nisi esse incididunt pariatur minim. Ex velit magna Lorem irure sunt est non sint ex. Consequat excepteur pariatur ipsum minim.\r\n","registered":"2014-01-29T04:19:41 -07:00","tags":["proident","labore","laborum","consectetur","ex","deserunt","eu"],"friends":[{"id":0,"name":"Mckee Barker"},{"id":1,"name":"Singleton Rosario"},{"id":2,"name":"Roy English"}],"greeting":"Hello, Peck Bradley! You have 1 unread messages.","favoriteFruit":"pear","location":{"latitude":4.857179,"longitude":-29.655426},"docFormat":"json"}