{"_id":"55ee5e98a9bab25ab558a941","index":2275,"guid":"90a65556-51c1-4b06-b0c1-2c01267621ea","isActive":true,"balance":"$28,594.49","picture":"http://placehold.it/32x32","age":41,"eyeColor":"amethyst","name":"Kinney Stevens","gender":"male","company":"CUBICIDE","email":"kinneystevens@cubicide.com","phone":"+1 (977) 583-2865","address":"291 Manhattan Court, Garfield, Wisconsin, 917","about":"Nulla elit excepteur in et dolor excepteur magna irure aliqua cupidatat officia. Adipisicing ad et Lorem officia et anim labore nostrud irure anim nisi. Lorem dolore ad velit pariatur duis fugiat minim do dolor amet laborum. Ipsum reprehenderit eu nostrud anim officia velit in amet sit quis pariatur. Elit labore ad aliquip nisi. Pariatur eu tempor officia deserunt sunt magna occaecat. Nostrud nulla ea nostrud dolore cillum consequat nulla anim magna occaecat.\r\n","registered":"2015-02-01T12:24:03 -07:00","tags":["amet","et","commodo","nisi","nisi","fugiat","eu"],"friends":[{"id":0,"name":"Chen Horne"},{"id":1,"name":"Eliza Byers"},{"id":2,"name":"Ernestine Estes"}],"greeting":"Hello, Kinney Stevens! You have 1 unread messages.","favoriteFruit":"strawberry","location":{"latitude":-62.237937,"longitude":98.757173},"docFormat":"json"}