{"_id":"55ee5e98b1a04f359584ebde","index":2069,"guid":"28930d17-e087-4dcf-b6a0-b36e2f9e1883","isActive":false,"balance":"$41,077.65","picture":"http://placehold.it/32x32","age":66,"eyeColor":"brown","name":"Flores Blair","gender":"male","company":"PYRAMAX","email":"floresblair@pyramax.com","phone":"+1 (895) 567-2681","address":"407 Buffalo Avenue, Smeltertown, Connecticut, 9408","about":"Duis irure nisi dolore irure esse irure velit ex quis ad sunt consectetur. Esse aute minim elit enim esse dolor reprehenderit incididunt occaecat commodo minim nisi ut consequat. Duis voluptate eu pariatur elit veniam qui culpa culpa ipsum.\r\n","registered":"2015-02-23T11:52:03 -07:00","tags":["laborum","consequat","non","in","incididunt","nulla","id"],"friends":[{"id":0,"name":"Gloria Petersen"},{"id":1,"name":"Anne Harper"},{"id":2,"name":"Cora Forbes"}],"greeting":"Hello, Flores Blair! You have 1 unread messages.","favoriteFruit":"strawberry","location":{"latitude":66.247516,"longitude":75.26705},"docFormat":"json"}