{"_id":"55ee5e45964203510b458c2d","index":1875,"guid":"74bd2d60-3b74-4373-a994-c1f1ffb64cc4","isActive":false,"balance":"$64,495.79","picture":"http://placehold.it/32x32","age":60,"eyeColor":"blue","name":"Violet Kidd","gender":"female","company":"PEARLESEX","email":"violetkidd@pearlesex.com","phone":"+1 (997) 580-2984","address":"896 Ryder Street, Moscow, Marshall Islands, 4435","about":"In et qui et et aliqua reprehenderit magna nisi mollit qui. Incididunt cupidatat cillum est duis reprehenderit enim esse. Do mollit dolore velit veniam enim. Do reprehenderit Lorem eiusmod irure est. Quis consectetur enim elit est non commodo tempor nostrud quis aute veniam cupidatat eiusmod.\r\n","registered":"2014-03-29T06:00:09 -07:00","tags":["elit","mollit","magna","duis","nulla","eu","pariatur"],"friends":[{"id":0,"name":"Corinne Nolan"},{"id":1,"name":"Riddle Raymond"},{"id":2,"name":"Alma Hancock"}],"greeting":"Hello, Violet Kidd! You have 3 unread messages.","favoriteFruit":"banana","location":{"latitude":-0.91613,"longitude":-125.821107},"docFormat":"json"}