{"_id":"55ee5e45f14f7d735a2511eb","index":1803,"guid":"7c831373-868e-4ab6-8fb1-30116c426198","isActive":false,"balance":"$50,856.34","picture":"http://placehold.it/32x32","age":53,"eyeColor":"green","name":"Karla Glass","gender":"female","company":"ASSITIA","email":"karlaglass@assitia.com","phone":"+1 (932) 416-3139","address":"954 Suydam Place, Blandburg, Ohio, 8213","about":"Sit non sit deserunt irure incididunt. Minim proident commodo minim reprehenderit dolor. Quis et labore laboris ea non dolore. Esse exercitation incididunt ullamco aliqua cupidatat eiusmod amet fugiat velit commodo aute. Non non sint anim commodo incididunt voluptate incididunt do irure consequat esse nulla et. Qui veniam magna voluptate ex nulla.\r\n","registered":"2014-01-01T05:22:43 -07:00","tags":["pariatur","ea","labore","cupidatat","voluptate","mollit","nulla"],"friends":[{"id":0,"name":"Owen Schwartz"},{"id":1,"name":"Charlotte Sandoval"},{"id":2,"name":"Valeria Sheppard"}],"greeting":"Hello, Karla Glass! You have 10 unread messages.","favoriteFruit":"strawberry","location":{"latitude":5.697237,"longitude":32.623298},"docFormat":"json"}