{"_id":"55ee5e45438297f271a84119","index":1746,"guid":"515b7762-84e9-4fee-a01b-6494d2baba1b","isActive":true,"balance":"$56,125.99","picture":"http://placehold.it/32x32","age":58,"eyeColor":"green","name":"Luna Armstrong","gender":"male","company":"ACCEL","email":"lunaarmstrong@accel.com","phone":"+1 (830) 438-2629","address":"768 Pierrepont Place, Swartzville, Alabama, 902","about":"Veniam eu ullamco dolor esse laboris fugiat aliqua ut et. Occaecat voluptate est enim deserunt in non sit sit voluptate deserunt ad culpa irure. Adipisicing minim Lorem laborum eu minim id excepteur dolore cillum excepteur consectetur aliqua.\r\n","registered":"2015-05-09T10:53:20 -07:00","tags":["dolore","do","nostrud","laboris","dolore","eiusmod","aliqua"],"friends":[{"id":0,"name":"Effie Hurley"},{"id":1,"name":"Elvia Dunn"},{"id":2,"name":"Matilda Bishop"}],"greeting":"Hello, Luna Armstrong! You have 2 unread messages.","favoriteFruit":"strawberry","location":{"latitude":36.971119,"longitude":-78.664126},"docFormat":"json"}