{"_id":"55ee5e44378c41abd9b9ce40","index":554,"guid":"e051cd35-3ec6-481b-b507-538627a16c1d","isActive":false,"balance":"$90,181.81","picture":"http://placehold.it/32x32","age":59,"eyeColor":"brown","name":"Debra Frank","gender":"female","company":"ZOID","email":"debrafrank@zoid.com","phone":"+1 (870) 512-3617","address":"479 Woodruff Avenue, Madrid, District Of Columbia, 616","about":"Commodo ipsum irure veniam deserunt duis. Anim officia ex qui eu duis anim pariatur eu nostrud cupidatat cillum dolore dolore. Excepteur qui ea minim est nisi sit ea ullamco sint sint occaecat nisi. Incididunt labore nulla qui eu velit ullamco et eu. Tempor aliquip excepteur officia mollit sunt excepteur anim consectetur ea duis fugiat dolor occaecat occaecat. Ullamco enim et est incididunt cupidatat aliqua velit irure minim. Do sunt in cupidatat duis ullamco dolore cupidatat sint laboris magna eiusmod pariatur laboris.\r\n","registered":"2014-07-23T06:23:04 -07:00","tags":["aliquip","eiusmod","officia","nostrud","sit","ullamco","labore"],"friends":[{"id":0,"name":"Doreen Glass"},{"id":1,"name":"Mckenzie Schwartz"},{"id":2,"name":"Shawn Sandoval"}],"greeting":"Hello, Debra Frank! You have 8 unread messages.","favoriteFruit":"strawberry","location":{"latitude":49.053789,"longitude":-40.713913},"docFormat":"json"}