{"_id":"55ee5e44b927f6987a29b899","index":820,"guid":"f9d22a0d-31a5-4421-8e6d-40059447617e","isActive":false,"balance":"$37,190.65","picture":"http://placehold.it/32x32","age":21,"eyeColor":"green","name":"Mercer Mclaughlin","gender":"male","company":"MULTRON","email":"mercermclaughlin@multron.com","phone":"+1 (918) 533-3066","address":"580 Dekoven Court, Abiquiu, Kansas, 4077","about":"Duis duis exercitation mollit consequat Lorem. In sunt voluptate deserunt officia aute tempor anim. Non occaecat enim enim incididunt ullamco incididunt esse adipisicing in laborum ut. Dolore do consectetur esse deserunt cillum nulla culpa ipsum commodo voluptate eiusmod. Exercitation in eiusmod ut ea dolor nostrud officia. Ex duis ut amet nostrud consequat deserunt qui consequat qui anim Lorem velit do. Velit ea et consectetur consequat cupidatat Lorem.\r\n","registered":"2014-06-21T03:00:50 -07:00","tags":["esse","incididunt","aute","enim","esse","adipisicing","laboris"],"friends":[{"id":0,"name":"Buckner Ayala"},{"id":1,"name":"Flowers Clemons"},{"id":2,"name":"Melinda Nieves"}],"greeting":"Hello, Mercer Mclaughlin! You have 10 unread messages.","favoriteFruit":"apple","location":{"latitude":74.757146,"longitude":-114.085799},"docFormat":"json"}