{"_id":"55ee5e44772ff453d24e8cff","index":915,"guid":"c3a7f51b-d422-45da-ae5e-e8eb915eab46","isActive":false,"balance":"$37,760.50","picture":"http://placehold.it/32x32","age":57,"eyeColor":"blue","name":"Robyn Ferrell","gender":"female","company":"FIBRODYNE","email":"robynferrell@fibrodyne.com","phone":"+1 (912) 585-3514","address":"376 Noel Avenue, Aberdeen, North Carolina, 2477","about":"Deserunt voluptate nisi nulla excepteur sunt nulla est mollit sunt. Et do ea pariatur adipisicing minim proident dolore magna. Veniam dolore ullamco sit deserunt deserunt est qui. Ullamco occaecat exercitation ut Lorem. Aute ex eiusmod et tempor ipsum occaecat in nulla ut.\r\n","registered":"2015-01-21T12:20:18 -07:00","tags":["laborum","qui","nulla","nulla","amet","ut","incididunt"],"friends":[{"id":0,"name":"Wendy Sweeney"},{"id":1,"name":"Christy Macias"},{"id":2,"name":"Darcy Bush"}],"greeting":"Hello, Robyn Ferrell! You have 4 unread messages.","favoriteFruit":"pear","location":{"latitude":48.946518,"longitude":85.989162},"docFormat":"json"}