{"_id":"55ee5e440e3bfef2981fb0f7","index":161,"guid":"416355f4-b786-4abb-b324-bc9192d8f696","isActive":true,"balance":"$31,997.80","picture":"http://placehold.it/32x32","age":37,"eyeColor":"blue","name":"Jordan West","gender":"female","company":"CEMENTION","email":"jordanwest@cemention.com","phone":"+1 (926) 549-3108","address":"922 Bergen Place, Grahamtown, North Carolina, 5554","about":"Aliquip nulla ad pariatur officia exercitation exercitation eu ea magna sunt eu. Sint esse fugiat ut ullamco. Qui amet enim esse non aliqua velit Lorem ipsum id aliqua nisi nulla magna. Nulla consectetur incididunt in amet est proident tempor. Incididunt incididunt eiusmod officia officia.\r\n","registered":"2014-11-19T05:28:56 -07:00","tags":["proident","dolore","nostrud","ipsum","irure","irure","reprehenderit"],"friends":[{"id":0,"name":"Marina Hendrix"},{"id":1,"name":"Betsy Vinson"},{"id":2,"name":"Maggie Petty"}],"greeting":"Hello, Jordan West! You have 4 unread messages.","favoriteFruit":"banana","location":{"latitude":12.866519,"longitude":103.481421},"docFormat":"json"}