{"_id":"55ee5e98643b6bd0a5104c17","index":2445,"guid":"b9ca3c10-b1e9-4409-8c5c-a3cb6c173d86","isActive":false,"balance":"$53,142.91","picture":"http://placehold.it/32x32","age":35,"eyeColor":"brown","name":"Sims Morrow","gender":"male","company":"RONELON","email":"simsmorrow@ronelon.com","phone":"+1 (961) 406-3523","address":"523 Crooke Avenue, Vicksburg, Iowa, 6672","about":"Exercitation consectetur aute dolor commodo velit dolor aute fugiat et elit labore id nostrud. Duis fugiat cupidatat qui exercitation ut. Incididunt duis ipsum laboris ipsum pariatur ut laboris non sunt mollit cupidatat aliqua. Nulla elit excepteur laboris culpa ipsum cillum ad mollit eiusmod consectetur. Proident Lorem mollit velit nostrud aliquip qui occaecat amet occaecat eiusmod incididunt velit. Irure do adipisicing incididunt est nulla fugiat sit voluptate aute qui eu. Ad voluptate sit sint qui enim ullamco ad.\r\n","registered":"2014-06-15T04:11:58 -07:00","tags":["velit","amet","ipsum","eu","ullamco","cupidatat","aliquip"],"friends":[{"id":0,"name":"Kelley Roy"},{"id":1,"name":"Marquez Everett"},{"id":2,"name":"Velazquez Sears"}],"greeting":"Hello, Sims Morrow! You have 5 unread messages.","favoriteFruit":"apple","location":{"latitude":-31.996739,"longitude":170.297038},"docFormat":"json"}