{"_id":"55ee5e45f36adc3b33c7c128","index":1930,"guid":"6441297b-0693-47fa-97b2-b5f8055c8ac3","isActive":true,"balance":"$24,686.89","picture":"http://placehold.it/32x32","age":69,"eyeColor":"brown","name":"Marianne Hicks","gender":"female","company":"ZIZZLE","email":"mariannehicks@zizzle.com","phone":"+1 (916) 465-2819","address":"619 Saratoga Avenue, Westerville, Arkansas, 2855","about":"Et dolor incididunt culpa nisi. Ut occaecat laborum esse ea non nisi et non ex ipsum aute aliquip dolore dolor. Ut do cupidatat commodo consequat occaecat esse nostrud non Lorem deserunt. Ullamco nulla exercitation cillum in duis Lorem adipisicing deserunt labore fugiat amet fugiat commodo. In sunt enim duis exercitation consequat culpa minim laboris fugiat. Voluptate est ad ullamco exercitation reprehenderit enim tempor qui sit. Excepteur et exercitation irure ullamco aute laboris nisi magna aute mollit.\r\n","registered":"2015-07-17T04:08:52 -07:00","tags":["excepteur","consectetur","velit","ipsum","aliqua","commodo","ex"],"friends":[{"id":0,"name":"Estella Rosa"},{"id":1,"name":"Randall Weiss"},{"id":2,"name":"Nicholson Edwards"}],"greeting":"Hello, Marianne Hicks! You have 9 unread messages.","favoriteFruit":"pear","location":{"latitude":72.506643,"longitude":94.528111},"docFormat":"json"}