{"_id":"55ee5e44caf4cd35522b2083","index":660,"guid":"e1bf761d-ceb1-41bb-aa35-80ad4fecbf56","isActive":false,"balance":"$3,662.36","picture":"http://placehold.it/32x32","age":60,"eyeColor":"blue","name":"Earlene Whitehead","gender":"female","company":"VETRON","email":"earlenewhitehead@vetron.com","phone":"+1 (900) 506-2301","address":"114 Bridge Street, Biddle, Federated States Of Micronesia, 4428","about":"Qui esse do ex consequat nostrud dolor veniam adipisicing incididunt eu qui sunt. Id nulla sint officia magna voluptate adipisicing reprehenderit aliqua aliqua Lorem. Cupidatat incididunt aute ex consectetur eu ea. Exercitation eiusmod elit qui irure. Magna in incididunt ullamco esse sit laboris consectetur enim aute laboris. Laborum et nulla velit ipsum.\r\n","registered":"2014-12-30T02:41:15 -07:00","tags":["dolor","labore","aliquip","velit","sint","sunt","consequat"],"friends":[{"id":0,"name":"Vaughn Goff"},{"id":1,"name":"Norman West"},{"id":2,"name":"Wells Hendrix"}],"greeting":"Hello, Earlene Whitehead! You have 8 unread messages.","favoriteFruit":"apple","location":{"latitude":0.980994,"longitude":-43.66401},"docFormat":"json"}