{"_id":"55ee5e443ff490702982172f","index":863,"guid":"b9f4459f-680b-4d6d-b0b4-69c3c79067de","isActive":false,"balance":"$72,718.65","picture":"http://placehold.it/32x32","age":45,"eyeColor":"green","name":"Leona Odonnell","gender":"female","company":"COREPAN","email":"leonaodonnell@corepan.com","phone":"+1 (955) 435-2687","address":"717 Seaview Avenue, Eden, Palau, 7607","about":"Reprehenderit aliquip proident ea occaecat aute ad. Aliquip esse nisi ex cupidatat veniam enim incididunt ex nisi culpa culpa cillum reprehenderit. Eu aliqua Lorem anim adipisicing consequat. Ullamco anim esse exercitation fugiat et magna adipisicing aliqua irure sint. Ex mollit est officia enim id. Irure eu cupidatat reprehenderit aute adipisicing consectetur do qui non id ut.\r\n","registered":"2014-01-26T12:09:24 -07:00","tags":["ex","sit","consequat","consectetur","amet","nostrud","sit"],"friends":[{"id":0,"name":"Wood Atkins"},{"id":1,"name":"Taylor Dickson"},{"id":2,"name":"Booth Chavez"}],"greeting":"Hello, Leona Odonnell! You have 1 unread messages.","favoriteFruit":"pear","location":{"latitude":21.183138,"longitude":73.98225},"docFormat":"json"}