{"_id":"55ee5e98da6421c99b069fc0","index":2812,"guid":"ec347c9f-4ad0-4605-a351-b048fa657993","isActive":true,"balance":"$9,913.59","picture":"http://placehold.it/32x32","age":42,"eyeColor":"amethyst","name":"Liza Harmon","gender":"female","company":"ZISIS","email":"lizaharmon@zisis.com","phone":"+1 (804) 438-2699","address":"287 Harbor Lane, Jessie, Utah, 7852","about":"Eu magna in deserunt ex sit fugiat exercitation ut. Exercitation aute incididunt eiusmod ipsum id exercitation id Lorem. Proident labore elit exercitation velit consectetur sit nulla sit et dolore ipsum. Voluptate ullamco pariatur magna labore consectetur aliqua consequat. Ullamco culpa qui fugiat proident sint dolore proident ullamco et. Culpa ullamco officia irure Lorem excepteur amet ea. Do minim aute ipsum ipsum amet proident eu voluptate ea tempor mollit id sit.\r\n","registered":"2014-03-24T12:25:23 -07:00","tags":["qui","tempor","non","ipsum","consectetur","tempor","aliqua"],"friends":[{"id":0,"name":"Frank Wyatt"},{"id":1,"name":"Cara Freeman"},{"id":2,"name":"Juliette Emerson"}],"greeting":"Hello, Liza Harmon! You have 5 unread messages.","favoriteFruit":"apple","location":{"latitude":59.592475,"longitude":162.961317},"docFormat":"json"}