{"_id":"55ee5e449135742be67182f2","index":757,"guid":"e8a033f4-3db0-4b39-baba-7486cfd56d4d","isActive":false,"balance":"$50,722.88","picture":"http://placehold.it/32x32","age":47,"eyeColor":"brown","name":"Wanda Foley","gender":"female","company":"OCTOCORE","email":"wandafoley@octocore.com","phone":"+1 (928) 442-2150","address":"352 Frank Court, Allentown, Northern Mariana Islands, 9495","about":"Sunt proident ipsum culpa elit eu ex aliquip do. Ex Lorem eu eiusmod eiusmod magna fugiat quis nulla enim non. Excepteur nostrud duis aliqua quis do nisi quis esse anim magna magna minim eu tempor. Consequat velit pariatur sunt magna deserunt. Fugiat incididunt minim ipsum mollit commodo minim Lorem. Nisi eiusmod eiusmod reprehenderit aliquip ad labore amet nostrud.\r\n","registered":"2015-04-16T02:59:53 -07:00","tags":["pariatur","eiusmod","excepteur","fugiat","adipisicing","deserunt","ea"],"friends":[{"id":0,"name":"Estes Ortiz"},{"id":1,"name":"Reyna Merrill"},{"id":2,"name":"Hamilton Carrillo"}],"greeting":"Hello, Wanda Foley! You have 4 unread messages.","favoriteFruit":"apple","location":{"latitude":0.272045,"longitude":-19.210166},"docFormat":"json"}