{"_id":"55ee5e9888e65c6a548b933f","index":2553,"guid":"288e3203-a299-459c-b8ef-a6bd56f1a099","isActive":true,"balance":"$1,826.88","picture":"http://placehold.it/32x32","age":57,"eyeColor":"hazel","name":"Savage Riddle","gender":"male","company":"SPHERIX","email":"savageriddle@spherix.com","phone":"+1 (911) 573-2411","address":"482 Foster Avenue, Williamson, Washington, 8370","about":"Esse occaecat eu ullamco officia sit nulla. Laborum culpa anim esse nostrud eiusmod do amet non ullamco duis dolor aute. Mollit quis voluptate duis aute deserunt in fugiat ut. Veniam magna nisi velit id in Lorem fugiat ullamco sunt duis tempor commodo reprehenderit anim. Ad aliqua ad non laboris aliquip. Nulla duis ipsum eiusmod amet consequat ad reprehenderit pariatur duis aliqua.\r\n","registered":"2014-02-27T05:58:33 -07:00","tags":["incididunt","ad","pariatur","anim","id","est","mollit"],"friends":[{"id":0,"name":"Clarke Montgomery"},{"id":1,"name":"Shauna Kelly"},{"id":2,"name":"Stone Ruiz"}],"greeting":"Hello, Savage Riddle! You have 2 unread messages.","favoriteFruit":"strawberry","location":{"latitude":-68.848347,"longitude":69.71844},"docFormat":"json"}