{"_id":"55ee5e9841ee9ee36ad0e5bb","index":2359,"guid":"a25ae0ff-abc7-4860-976c-1d065e2bda5b","isActive":false,"balance":"$14,496.44","picture":"http://placehold.it/32x32","age":66,"eyeColor":"hazel","name":"Casey Holden","gender":"male","company":"FREAKIN","email":"caseyholden@freakin.com","phone":"+1 (908) 589-3743","address":"871 McClancy Place, Coventry, Connecticut, 1887","about":"Dolore et anim sint ad et exercitation cillum in. Sint fugiat ut officia ad et officia ex ad adipisicing officia aute. Eu sit consequat esse esse nisi anim irure ex ipsum magna in adipisicing pariatur proident. Aliqua cillum nostrud officia sint proident laborum officia velit enim elit ut elit commodo sint. Pariatur sit eu consequat veniam exercitation non minim ut sunt eu id aute cupidatat consectetur. Elit Lorem enim sit laborum amet.\r\n","registered":"2014-07-24T03:22:00 -07:00","tags":["sint","sint","veniam","duis","sint","ad","labore"],"friends":[{"id":0,"name":"Floyd Jackson"},{"id":1,"name":"Clay Bass"},{"id":2,"name":"Fran Cohen"}],"greeting":"Hello, Casey Holden! You have 1 unread messages.","favoriteFruit":"strawberry","location":{"latitude":-51.083993,"longitude":156.336922},"docFormat":"json"}