{"_id":"55ee5e9842bd038fad6d64fb","index":2788,"guid":"10969918-2f87-4906-a5fe-c69045fb8d81","isActive":true,"balance":"$93,713.52","picture":"http://placehold.it/32x32","age":26,"eyeColor":"green","name":"Bridget Chen","gender":"female","company":"PARLEYNET","email":"bridgetchen@parleynet.com","phone":"+1 (897) 522-3045","address":"157 Plymouth Street, Bodega, New Hampshire, 1846","about":"Anim cupidatat adipisicing ea dolore non ea quis. Deserunt dolor laborum excepteur sint magna ullamco do. Ea minim excepteur ea cupidatat nisi commodo consequat sint. Ex deserunt adipisicing dolor aute magna culpa consectetur quis non. Irure ipsum commodo excepteur ullamco ut sint ullamco eu labore exercitation. Lorem laborum veniam dolor nulla amet ea reprehenderit consequat enim non veniam cupidatat non. Et adipisicing in occaecat tempor mollit veniam.\r\n","registered":"2015-04-30T06:03:12 -07:00","tags":["velit","dolor","irure","commodo","amet","non","do"],"friends":[{"id":0,"name":"Krista Becker"},{"id":1,"name":"Latisha Dudley"},{"id":2,"name":"Kelly Rosa"}],"greeting":"Hello, Bridget Chen! You have 7 unread messages.","favoriteFruit":"orange","location":{"latitude":-27.263713,"longitude":-129.506202},"docFormat":"json"}