{"_id":"55ee5e44e95e0d8b5b46671c","index":546,"guid":"b2592532-eec9-4bc6-a727-dc84458608f5","isActive":false,"balance":"$27,459.39","picture":"http://placehold.it/32x32","age":54,"eyeColor":"green","name":"Soto Cobb","gender":"male","company":"AMTAP","email":"sotocobb@amtap.com","phone":"+1 (865) 471-3618","address":"501 Atlantic Avenue, Jacksonwald, Virginia, 6127","about":"Enim esse ipsum aliqua id incididunt sint amet dolore sint reprehenderit. Anim enim adipisicing aliquip aliqua mollit est nulla excepteur sunt velit. Elit occaecat mollit est ipsum duis nisi aute culpa ut occaecat fugiat incididunt qui. Do labore reprehenderit dolore officia occaecat ea reprehenderit mollit voluptate laborum esse aute ut magna. In dolor aliquip quis aliqua ullamco do. Id commodo sit ut eu deserunt cupidatat ut ullamco esse dolore qui. Duis sit laboris consectetur aute aliquip sint ut veniam officia.\r\n","registered":"2014-01-02T12:16:17 -07:00","tags":["nulla","sint","qui","nisi","et","laborum","tempor"],"friends":[{"id":0,"name":"Alford Hensley"},{"id":1,"name":"Keisha Little"},{"id":2,"name":"Ball Mann"}],"greeting":"Hello, Soto Cobb! You have 9 unread messages.","favoriteFruit":"banana","location":{"latitude":26.410588,"longitude":-93.428112},"docFormat":"json"}