{"_id":"55ee5e98049b65d47564a737","index":2402,"guid":"2010d1f4-052f-493b-b34d-512d3c5b8efb","isActive":false,"balance":"$32,528.24","picture":"http://placehold.it/32x32","age":68,"eyeColor":"honey","name":"Marsh Lyons","gender":"male","company":"ZIORE","email":"marshlyons@ziore.com","phone":"+1 (864) 448-2162","address":"423 Brown Street, Movico, Palau, 8825","about":"Quis minim nulla dolore sit velit proident excepteur duis ea cillum do reprehenderit do adipisicing. Sunt in nisi enim culpa dolore tempor irure. Do voluptate esse mollit laboris ad consequat commodo occaecat magna cupidatat veniam. Ex irure do consectetur aliqua culpa ipsum sint minim ipsum quis consectetur proident Lorem ut.\r\n","registered":"2015-03-08T11:19:12 -07:00","tags":["laborum","ea","amet","sit","nisi","laboris","non"],"friends":[{"id":0,"name":"Candy Sawyer"},{"id":1,"name":"York Lucas"},{"id":2,"name":"Mayra Mcguire"}],"greeting":"Hello, Marsh Lyons! You have 6 unread messages.","favoriteFruit":"banana","location":{"latitude":48.427163,"longitude":94.572289},"docFormat":"json"}