{"_id":"55ee5e45133ac2f38768f96d","index":1577,"guid":"b4451eeb-fb08-42a9-a770-d7020b39a9f1","isActive":true,"balance":"$59,382.06","picture":"http://placehold.it/32x32","age":50,"eyeColor":"blue","name":"Dickson Dixon","gender":"male","company":"FLEETMIX","email":"dicksondixon@fleetmix.com","phone":"+1 (868) 477-2034","address":"964 Fillmore Avenue, Irwin, California, 8317","about":"Amet minim eu minim proident amet nostrud laboris adipisicing laborum deserunt culpa duis aliquip. Sunt voluptate Lorem laboris excepteur minim et. Consectetur labore velit laborum in velit. Nisi ullamco nulla sunt sit nostrud voluptate excepteur dolore irure ipsum. Nisi sunt exercitation deserunt laborum tempor amet do fugiat adipisicing sit labore eu.\r\n","registered":"2015-06-07T10:55:23 -07:00","tags":["elit","consequat","dolore","culpa","ullamco","excepteur","veniam"],"friends":[{"id":0,"name":"Leticia Crawford"},{"id":1,"name":"Sasha Gallegos"},{"id":2,"name":"Charlene Stark"}],"greeting":"Hello, Dickson Dixon! You have 6 unread messages.","favoriteFruit":"strawberry","location":{"latitude":80.505989,"longitude":-123.170016},"docFormat":"json"}