{"_id":"55ee5e9850138b6578da166e","index":2155,"guid":"b45d435a-01c8-467b-a722-ea3a28cce659","isActive":false,"balance":"$7,609.38","picture":"http://placehold.it/32x32","age":58,"eyeColor":"hazel","name":"Lynnette Le","gender":"female","company":"ISONUS","email":"lynnettele@isonus.com","phone":"+1 (975) 470-2540","address":"955 Meeker Avenue, Fairfield, Iowa, 8960","about":"Ea ipsum pariatur sint pariatur eu labore quis aliqua nulla et reprehenderit. Sit ex aute sunt veniam velit. Velit ullamco cillum id deserunt laborum aliquip exercitation voluptate commodo. Non dolore nisi eu eu aute irure cupidatat ea minim mollit incididunt.\r\n","registered":"2015-05-26T12:24:33 -07:00","tags":["voluptate","sit","nulla","et","sunt","qui","laboris"],"friends":[{"id":0,"name":"Duffy Mejia"},{"id":1,"name":"May Jimenez"},{"id":2,"name":"Lynn Garcia"}],"greeting":"Hello, Lynnette Le! You have 9 unread messages.","favoriteFruit":"orange","location":{"latitude":39.945288,"longitude":-93.705789},"docFormat":"json"}