{"_id":"55ee5e98f14acb1d79002b72","index":2322,"guid":"8dbb408a-f22f-4eae-981c-2c6b0ed601a0","isActive":false,"balance":"$41,757.53","picture":"http://placehold.it/32x32","age":54,"eyeColor":"amethyst","name":"Virginia Burt","gender":"female","company":"CENTREGY","email":"virginiaburt@centregy.com","phone":"+1 (825) 531-2792","address":"609 Goodwin Place, Lumberton, Kentucky, 6613","about":"Cillum dolore nostrud magna amet quis exercitation sint adipisicing proident eu ea sunt velit reprehenderit. Nisi do reprehenderit excepteur dolor. Exercitation ad sit tempor anim. Minim est laborum ad culpa cupidatat aliqua. Lorem minim adipisicing commodo irure incididunt minim occaecat aute labore nostrud consectetur voluptate. Lorem labore nostrud pariatur ipsum officia voluptate occaecat.\r\n","registered":"2014-07-16T05:56:52 -07:00","tags":["mollit","eu","ullamco","ea","qui","nostrud","adipisicing"],"friends":[{"id":0,"name":"Ina Booth"},{"id":1,"name":"Juana Montoya"},{"id":2,"name":"Blake Pate"}],"greeting":"Hello, Virginia Burt! You have 2 unread messages.","favoriteFruit":"strawberry","location":{"latitude":-85.01977,"longitude":134.273368},"docFormat":"json"}