{"_id":"55ee5e44bb32fe1f6dfde27c","index":1471,"guid":"1628c207-844c-4047-9861-22cc0c87b500","isActive":true,"balance":"$60,319.18","picture":"http://placehold.it/32x32","age":42,"eyeColor":"blue","name":"Lynn Fleming","gender":"male","company":"FORTEAN","email":"lynnfleming@fortean.com","phone":"+1 (875) 562-3777","address":"931 Langham Street, Tooleville, Guam, 6725","about":"Ullamco et amet commodo esse irure officia laboris non elit aliquip proident. Ullamco dolor do esse ut fugiat. Occaecat ex non duis magna esse labore sit enim. Minim dolor aute consectetur fugiat et excepteur labore. Ut commodo pariatur nulla exercitation incididunt sunt. Elit ad ea irure non aute dolore excepteur fugiat culpa.\r\n","registered":"2015-06-26T05:52:59 -07:00","tags":["qui","nostrud","amet","deserunt","quis","consectetur","mollit"],"friends":[{"id":0,"name":"House Sloan"},{"id":1,"name":"Spencer Gilmore"},{"id":2,"name":"Callie Mccoy"}],"greeting":"Hello, Lynn Fleming! You have 2 unread messages.","favoriteFruit":"orange","location":{"latitude":-19.911768,"longitude":54.504238},"docFormat":"json"}