{"_id":"55ee5e4452efd61a34dcf516","index":257,"guid":"0f46e864-5168-4586-b710-11164c0eb804","isActive":false,"balance":"$44,778.71","picture":"http://placehold.it/32x32","age":69,"eyeColor":"blue","name":"Wanda Shaffer","gender":"female","company":"JAMNATION","email":"wandashaffer@jamnation.com","phone":"+1 (939) 585-2693","address":"338 Throop Avenue, Reinerton, Wyoming, 4633","about":"Elit ipsum irure ipsum incididunt ex deserunt excepteur velit aute sint dolor. Culpa eiusmod qui ea et aliqua aliqua ad proident fugiat commodo commodo aliqua. Magna velit deserunt et cillum. Id eiusmod qui ad laboris aute mollit do commodo occaecat. Laborum et nostrud excepteur do officia nisi deserunt. Esse adipisicing sit eiusmod eiusmod eiusmod nostrud exercitation ut pariatur.\r\n","registered":"2014-08-30T11:59:32 -07:00","tags":["tempor","culpa","id","ullamco","sit","laborum","elit"],"friends":[{"id":0,"name":"Reyna Ball"},{"id":1,"name":"Petty Foley"},{"id":2,"name":"Erin Ortiz"}],"greeting":"Hello, Wanda Shaffer! You have 10 unread messages.","favoriteFruit":"banana","location":{"latitude":-17.768634,"longitude":-141.165075},"docFormat":"json"}